fastapi_spam/__init__.py
fastapi_spam/constants.py
fastapi_spam/middleware.py
fastapi_spam/py.typed
fastapi_spam-0.0.4.dist-info/licenses/AUTHORS
fastapi_spam-0.0.4.dist-info/licenses/LICENSE
fastapi_spam-0.0.4.dist-info/METADATA
fastapi_spam-0.0.4.dist-info/WHEEL
fastapi_spam-0.0.4.dist-info/top_level.txt
fastapi_spam-0.0.4.dist-info/RECORD
