Metadata-Version: 2.4
Name: fastapi-spam
Version: 0.0.4
Summary: FastAPI middleware to redirect spam requests to a random 10 hours of video
Project-URL: Homepage, https://github.com/nickatnight/fastapi-spam
Project-URL: Issues, https://github.com/nickatnight/fastapi-spam/issues
Keywords: Python,package,packaging,FastAPI,Spam,Middleware
Classifier: Development Status :: 5 - Production/Stable
Classifier: Environment :: Console
Classifier: Framework :: FastAPI
Classifier: Intended Audience :: Developers
Classifier: Natural Language :: English
Classifier: Programming Language :: Python :: 3
Classifier: Programming Language :: Python :: 3.9
Classifier: Programming Language :: Python :: 3.10
Classifier: Programming Language :: Python :: 3.12
Classifier: Programming Language :: Python :: 3.13
Classifier: Typing :: Typed
Requires-Python: >=3.9
License-File: LICENSE
License-File: AUTHORS
Requires-Dist: starlette<0.48.0,>=0.40.0
Dynamic: license-file
